inkit/__init__.py
inkit/client.py
inkit/exceptions.py
inkit/extensions.py
inkit/metaclasses.py
inkit/products.py
inkit/resources.py
inkit/response_object.py
inkit/router.py
inkit/data/routing-config-map.json
inkit-1.0.5.dist-info/LICENSE
inkit-1.0.5.dist-info/METADATA
inkit-1.0.5.dist-info/WHEEL
inkit-1.0.5.dist-info/top_level.txt
inkit-1.0.5.dist-info/RECORD
