Metadata-Version: 2.1
Name: inkit
Version: 1.0.5
Summary: The world's leading Reach Enablement Platform
Home-page: https://github.com/inkit/inkit-python
Author: Inkit Inc
Author-email: engineering@inkit.com
Classifier: Programming Language :: Python :: 3
Classifier: License :: OSI Approved :: MIT License
Classifier: Operating System :: OS Independent
Requires-Python: >=3.6
License-File: LICENSE
Requires-Dist: urllib3
Requires-Dist: requests
